deutschland/pegel_online/__init__.py
deutschland/pegel_online/api/__init__.py
deutschland/pegel_online/api/measurement_api.py
deutschland/pegel_online/api/station_api.py
deutschland/pegel_online/api/water_api.py
deutschland/pegel_online/api_client.py
deutschland/pegel_online/apis/__init__.py
deutschland/pegel_online/configuration.py
deutschland/pegel_online/exceptions.py
deutschland/pegel_online/model/__init__.py
deutschland/pegel_online/model/comment.py
deutschland/pegel_online/model/comment_inner.py
deutschland/pegel_online/model/current_measurement.py
deutschland/pegel_online/model/measurement_result.py
deutschland/pegel_online/model/measurement_result_inner.py
deutschland/pegel_online/model/station.py
deutschland/pegel_online/model/station_overview_result.py
deutschland/pegel_online/model/station_water.py
deutschland/pegel_online/model/timeseries.py
deutschland/pegel_online/model/timeseries_gauge_zero.py
deutschland/pegel_online/model/timeseries_not_found.py
deutschland/pegel_online/model/water_result.py
deutschland/pegel_online/model_utils.py
deutschland/pegel_online/models/__init__.py
deutschland/pegel_online/rest.py
de_pegel_online-0.1.1.dist-info/METADATA
de_pegel_online-0.1.1.dist-info/WHEEL
de_pegel_online-0.1.1.dist-info/RECORD
